[
  {
    "id": 9001,
    "section": "QA Test",
    "category": "Simple Colors",
    "question": "Apples are what color?",
    "answers": [
      "red",
      "green"
    ],
    "choices": [
      "red",
      "green",
      "blue",
      "yellow"
    ],
    "answer_type": "color",
    "special_65_20": false
  },
  {
    "id": 9002,
    "section": "QA Test",
    "category": "Simple Colors",
    "question": "The sky is what color?",
    "answers": [
      "blue"
    ],
    "choices": [
      "blue",
      "red",
      "green",
      "black"
    ],
    "answer_type": "color",
    "special_65_20": false
  },
  {
    "id": 9003,
    "section": "QA Test",
    "category": "Simple Numbers",
    "question": "How many wheels does a bicycle have?",
    "answers": [
      "two"
    ],
    "aliases": [
      "2"
    ],
    "choices": [
      "two",
      "three",
      "four",
      "five"
    ],
    "answer_type": "number",
    "special_65_20": false
  },
  {
    "id": 9010,
    "section": "QA Test",
    "category": "Multi Answer Test",
    "question": "Name two colors on the American flag.",
    "answers": [
      "red",
      "white",
      "blue"
    ],
    "required_count": 2,
    "choices": [
      "red",
      "white",
      "blue",
      "green"
    ],
    "answer_type": "multi_color",
    "special_65_20": false
  },
  {
    "id": 9011,
    "section": "QA Test",
    "category": "Multi Answer Test",
    "question": "Name three common pets.",
    "answers": [
      "dog",
      "cat",
      "fish",
      "bird"
    ],
    "required_count": 3,
    "choices": [
      "dog",
      "cat",
      "fish",
      "bird",
      "tree",
      "car"
    ],
    "answer_type": "multi_simple",
    "special_65_20": false
  },
  {
    "id": 9012,
    "section": "QA Test",
    "category": "Multi Answer Test",
    "question": "Name two fruits.",
    "answers": [
      "apple",
      "banana",
      "orange",
      "grape"
    ],
    "required_count": 2,
    "choices": [
      "apple",
      "banana",
      "orange",
      "grape",
      "table",
      "chair"
    ],
    "answer_type": "multi_simple",
    "special_65_20": false
  },
  {
    "id": 9013,
    "section": "QA Test",
    "category": "USCIS Multi Answer Test",
    "question": "Name three national U.S. holidays.",
    "answers": [
      "New Year's Day",
      "Martin Luther King, Jr. Day",
      "Presidents Day",
      "Memorial Day",
      "Juneteenth",
      "Independence Day",
      "Labor Day",
      "Columbus Day",
      "Veterans Day",
      "Thanksgiving Day",
      "Christmas Day"
    ],
    "required_count": 3,
    "choices": [
      "New Year's Day",
      "Memorial Day",
      "Independence Day",
      "Labor Day",
      "Halloween",
      "Valentine's Day"
    ],
    "answer_type": "holiday",
    "special_65_20": false
  },
  {
    "id": 9014,
    "section": "QA Test",
    "category": "USCIS Multi Answer Test",
    "question": "Name two Cabinet-level positions.",
    "answers": [
      "Secretary of State",
      "Secretary of Defense",
      "Secretary of Education",
      "Secretary of Labor",
      "Attorney General",
      "Vice President"
    ],
    "required_count": 2,
    "choices": [
      "Secretary of State",
      "Secretary of Defense",
      "Attorney General",
      "Vice President",
      "Chief Justice",
      "Speaker of the House"
    ],
    "answer_type": "government",
    "special_65_20": false
  }
]